swanboard/__init__.py
swanboard/app.py
swanboard/callback.py
swanboard/package.json
swanboard/settings.py
swanboard/controller/chart.py
swanboard/controller/db.py
swanboard/controller/experiment.py
swanboard/controller/namespace.py
swanboard/controller/project.py
swanboard/controller/utils/__init__.py
swanboard/controller/utils/charts.py
swanboard/controller/utils/tag.py
swanboard/db/__init__.py
swanboard/db/db_connect.py
swanboard/db/error.py
swanboard/db/migrate.py
swanboard/db/model.py
swanboard/db/table_config.py
swanboard/db/docs/Errors.md
swanboard/db/docs/README.md
swanboard/db/models/__init__.py
swanboard/db/models/charts.py
swanboard/db/models/displays.py
swanboard/db/models/experiments.py
swanboard/db/models/namespaces.py
swanboard/db/models/projects.py
swanboard/db/models/sources.py
swanboard/db/models/tags.py
swanboard/db/utils/__init__.py
swanboard/db/utils/chart.py
swanboard/middleware/common.py
swanboard/module/__init__.py
swanboard/module/resp.py
swanboard/router/chart.py
swanboard/router/experiment.py
swanboard/router/media.py
swanboard/router/namespace.py
swanboard/router/project.py
swanboard/run/__init__.py
swanboard/run/run.py
swanboard/run/utils.py
swanboard/template/index.html
swanboard/template/assets/ChartPage-B6lQRR9c.js
swanboard/template/assets/ChartPage-DpIsI9DF.css
swanboard/template/assets/ChartsView-IOEsa2zj.js
swanboard/template/assets/EnvHardware-DkTn--4y.js
swanboard/template/assets/EnvIndex-CfAiEKK4.js
swanboard/template/assets/EnvRequirements-B5x5JJ2m.js
swanboard/template/assets/EnvironmentPage-BfQNbOhM.js
swanboard/template/assets/EnvironmentPage-DTT_cgyY.css
swanboard/template/assets/ExperimentView-Bf88h1eI.js
swanboard/template/assets/ExperimentView-Ce4FknkD.css
swanboard/template/assets/FuncBar-DE-BJajM.css
swanboard/template/assets/FuncBar-DxBJntCU.js
swanboard/template/assets/HelpView-4GFUdp0u.js
swanboard/template/assets/HomeView-C-0XiB-N.css
swanboard/template/assets/HomeView-F8vwsCw2.js
swanboard-0.1.6.dist-info/METADATA
swanboard-0.1.6.dist-info/WHEEL
swanboard-0.1.6.dist-info/RECORD
