Metadata-Version: 2.3
Name: swanboard
Version: 0.1.6
Summary: Dashboard for SwanLab.
Project-URL: Homepage, https://swanhub.co
Project-URL: Source, https://github.com/SwanHubX/SwanLab-Dashboard
Project-URL: Bug Reports, https://github.com/SwanHubX/SwanLab-Dashboard/issues
Author-email: Cunyue <team@swanhub.co>, Feudalman <team@swanhub.co>
License: Apache-2.0
Keywords: machine learning,reproducibility,visualization
Classifier: Development Status :: 3 - Alpha
Classifier: License :: OSI Approved :: Apache Software License
Classifier: Operating System :: OS Independent
Classifier: Programming Language :: Python :: 3
Classifier: Programming Language :: Python :: 3 :: Only
Classifier: Programming Language :: Python :: 3.8
Classifier: Programming Language :: Python :: 3.9
Classifier: Programming Language :: Python :: 3.10
Classifier: Programming Language :: Python :: 3.11
Classifier: Programming Language :: Python :: 3.12
Classifier: Topic :: Scientific/Engineering
Classifier: Topic :: Scientific/Engineering :: Artificial Intelligence
Classifier: Topic :: Scientific/Engineering :: Visualization
Requires-Python: >=3.8
Requires-Dist: fastapi>=0.110.1
Requires-Dist: peewee
Requires-Dist: psutil
Requires-Dist: setuptools
Requires-Dist: swankit
Requires-Dist: ujson
Requires-Dist: uvicorn>=0.14.0
